odoo/addons/project_milestone/README.rst
odoo/addons/project_milestone/__init__.py
odoo/addons/project_milestone/__manifest__.py
odoo/addons/project_milestone/i18n/de.po
odoo/addons/project_milestone/i18n/es.po
odoo/addons/project_milestone/i18n/es_AR.po
odoo/addons/project_milestone/i18n/es_ES.po
odoo/addons/project_milestone/i18n/fi.po
odoo/addons/project_milestone/i18n/fr.po
odoo/addons/project_milestone/i18n/fr_FR.po
odoo/addons/project_milestone/i18n/it.po
odoo/addons/project_milestone/i18n/project_milestone.pot
odoo/addons/project_milestone/i18n/sl.po
odoo/addons/project_milestone/models/__init__.py
odoo/addons/project_milestone/models/project.py
odoo/addons/project_milestone/models/project_milestone.py
odoo/addons/project_milestone/models/project_task.py
odoo/addons/project_milestone/readme/CONTRIBUTORS.rst
odoo/addons/project_milestone/readme/DESCRIPTION.rst
odoo/addons/project_milestone/readme/HISTORY.rst
odoo/addons/project_milestone/readme/USAGE.rst
odoo/addons/project_milestone/security/ir.model.access.csv
odoo/addons/project_milestone/static/description/icon.png
odoo/addons/project_milestone/static/description/index.html
odoo/addons/project_milestone/tests/__init__.py
odoo/addons/project_milestone/tests/test_project_milestone.py
odoo/addons/project_milestone/views/project.xml
odoo/addons/project_milestone/views/project_milestone.xml
odoo/addons/project_milestone/views/project_task.xml
odoo14_addon_project_milestone-14.0.1.4.1.dist-info/METADATA
odoo14_addon_project_milestone-14.0.1.4.1.dist-info/WHEEL
odoo14_addon_project_milestone-14.0.1.4.1.dist-info/top_level.txt
odoo14_addon_project_milestone-14.0.1.4.1.dist-info/RECORD
